[
  {
    "ContainingType": "api.Controllers.TestController",
    "Method": "Get_From_DB",
    "RelativePath": "api/Test/GetFromDB",
    "HttpMethod": "GET",
    "IsController": true,
    "Order": 0,
    "Parameters": [],
    "ReturnTypes": [
      {
        "Type": "System.String",
        "MediaTypes": [
          "text/plain",
          "application/json",
          "text/json"
        ],
        "StatusCode": 200
      }
    ]
  },
  {
    "ContainingType": "api.Controllers.UserController",
    "Method": "GetUser",
    "RelativePath": "api/User/GetUser",
    "HttpMethod": "POST",
    "IsController": true,
    "Order": 0,
    "Parameters": [
      {
        "Name": "input",
        "Type": "Newtonsoft.Json.Linq.JObject",
        "IsRequired": true
      }
    ],
    "ReturnTypes": [
      {
        "Type": "api.Models.User",
        "MediaTypes": [
          "text/plain",
          "application/json",
          "text/json"
        ],
        "StatusCode": 200
      }
    ]
  }
]